[{"fair_coeff": 0.0, "zdim": 6, "test_results": {"test": {"acc": 0.75, "DP": 0.0, "EO": 0.0, "CF": 0.0}}}, {"fair_coeff": 0.0, "zdim": 7, "test_results": {"test": {"acc": 0.75, "DP": 0.0, "EO": 0.0, "CF": 0.0}}}, {"fair_coeff": 0.0, "zdim": 8, "test_results": {"test": {"acc": 0.75, "DP": 0.0, "EO": 0.0, "CF": 0.0}}}, {"fair_coeff": 0.0, "zdim": 9, "test_results": {"test": {"acc": 0.75, "DP": 0.0, "EO": 0.0, "CF": 0.0}}}, {"fair_coeff": 0.0, "zdim": 10, "test_results": {"test": {"acc": 0.75, "DP": 0.0, "EO": 0.0, "CF": 0.0}}}, {"fair_coeff": 0.0, "zdim": 11, "test_results": {"test": {"acc": 0.75, "DP": 0.0, "EO": 0.0, "CF": 0.0}}}, {"fair_coeff": 0.0, "zdim": 12, "test_results": {"test": {"acc": 0.75, "DP": 0.0, "EO": 0.0, "CF": 0.0}}}, {"fair_coeff": 0.0, "zdim": 13, "test_results": {"test": {"acc": 0.75, "DP": 0.0, "EO": 0.0, "CF": 0.0}}}, {"fair_coeff": 0.0, "zdim": 14, "test_results": {"test": {"acc": 0.75, "DP": 0.0, "EO": 0.0, "CF": 0.0}}}, {"fair_coeff": 0.0, "zdim": 15, "test_results": {"test": {"acc": 0.75, "DP": 0.0, "EO": 0.0, "CF": 0.0}}}, {"fair_coeff": 0.0, "zdim": 16, "test_results": {"test": {"acc": 0.75, "DP": 0.0, "EO": 0.0, "CF": 0.0}}}, {"fair_coeff": 0.0, "zdim": 17, "test_results": {"test": {"acc": 0.75, "DP": 0.0, "EO": 0.0, "CF": 0.0}}}, {"fair_coeff": 0.0, "zdim": 18, "test_results": {"test": {"acc": 0.75, "DP": 0.0, "EO": 0.0, "CF": 0.0}}}, {"fair_coeff": 0.0, "zdim": 19, "test_results": {"test": {"acc": 0.75, "DP": 0.0, "EO": 0.0, "CF": 0.0}}}, {"fair_coeff": 0.0, "zdim": 20, "test_results": {"test": {"acc": 0.75, "DP": 0.0, "EO": 0.0, "CF": 0.0}}}, {"fair_coeff": 0.1, "zdim": 6, "test_results": {"test": {"acc": 0.8661971830985915, "DP": 0.11217681401167642, "EO": 0.09216853408029876, "CF": 0.05130784708249497}}}, {"fair_coeff": 0.1, "zdim": 7, "test_results": {"test": {"acc": 0.8661971830985915, "DP": 0.11217681401167642, "EO": 0.09216853408029876, "CF": 0.05130784708249497}}}, {"fair_coeff": 0.1, "zdim": 8, "test_results": {"test": {"acc": 0.8661971830985915, "DP": 0.11217681401167642, "EO": 0.09216853408029876, "CF": 0.05130784708249497}}}, {"fair_coeff": 0.1, "zdim": 9, "test_results": {"test": {"acc": 0.8661971830985915, "DP": 0.11217681401167642, "EO": 0.09216853408029876, "CF": 0.05130784708249497}}}, {"fair_coeff": 0.1, "zdim": 10, "test_results": {"test": {"acc": 0.8661971830985915, "DP": 0.11217681401167642, "EO": 0.09216853408029876, "CF": 0.05130784708249497}}}, {"fair_coeff": 0.1, "zdim": 11, "test_results": {"test": {"acc": 0.8661971830985915, "DP": 0.11217681401167642, "EO": 0.09216853408029876, "CF": 0.05130784708249497}}}, {"fair_coeff": 0.1, "zdim": 12, "test_results": {"test": {"acc": 0.8661971830985915, "DP": 0.11217681401167642, "EO": 0.09216853408029876, "CF": 0.05130784708249497}}}, {"fair_coeff": 0.1, "zdim": 13, "test_results": {"test": {"acc": 0.8661971830985915, "DP": 0.11217681401167642, "EO": 0.09216853408029876, "CF": 0.05130784708249497}}}, {"fair_coeff": 0.1, "zdim": 14, "test_results": {"test": {"acc": 0.8661971830985915, "DP": 0.11217681401167642, "EO": 0.09216853408029876, "CF": 0.05130784708249497}}}, {"fair_coeff": 0.1, "zdim": 15, "test_results": {"test": {"acc": 0.8661971830985915, "DP": 0.11217681401167642, "EO": 0.09216853408029876, "CF": 0.05130784708249497}}}, {"fair_coeff": 0.1, "zdim": 16, "test_results": {"test": {"acc": 0.8661971830985915, "DP": 0.11217681401167642, "EO": 0.09216853408029876, "CF": 0.05130784708249497}}}, {"fair_coeff": 0.1, "zdim": 17, "test_results": {"test": {"acc": 0.8661971830985915, "DP": 0.11217681401167642, "EO": 0.09216853408029876, "CF": 0.05130784708249497}}}, {"fair_coeff": 0.1, "zdim": 18, "test_results": {"test": {"acc": 0.8661971830985915, "DP": 0.11217681401167642, "EO": 0.09216853408029876, "CF": 0.05130784708249497}}}, {"fair_coeff": 0.1, "zdim": 19, "test_results": {"test": {"acc": 0.8661971830985915, "DP": 0.11217681401167642, "EO": 0.09216853408029876, "CF": 0.05130784708249497}}}, {"fair_coeff": 0.1, "zdim": 20, "test_results": {"test": {"acc": 0.8661971830985915, "DP": 0.11217681401167642, "EO": 0.09216853408029876, "CF": 0.05130784708249497}}}, {"fair_coeff": 0.2, "zdim": 6, "test_results": {"test": {"acc": 0.75, "DP": 0.0, "EO": 0.0, "CF": 0.0}}}, {"fair_coeff": 0.2, "zdim": 7, "test_results": {"test": {"acc": 0.75, "DP": 0.0, "EO": 0.0, "CF": 0.0}}}, {"fair_coeff": 0.2, "zdim": 8, "test_results": {"test": {"acc": 0.75, "DP": 0.0, "EO": 0.0, "CF": 0.0}}}, {"fair_coeff": 0.2, "zdim": 9, "test_results": {"test": {"acc": 0.75, "DP": 0.0, "EO": 0.0, "CF": 0.0}}}, {"fair_coeff": 0.2, "zdim": 10, "test_results": {"test": {"acc": 0.75, "DP": 0.0, "EO": 0.0, "CF": 0.0}}}, {"fair_coeff": 0.2, "zdim": 11, "test_results": {"test": {"acc": 0.75, "DP": 0.0, "EO": 0.0, "CF": 0.0}}}, {"fair_coeff": 0.2, "zdim": 12, "test_results": {"test": {"acc": 0.75, "DP": 0.0, "EO": 0.0, "CF": 0.0}}}, {"fair_coeff": 0.2, "zdim": 13, "test_results": {"test": {"acc": 0.75, "DP": 0.0, "EO": 0.0, "CF": 0.0}}}, {"fair_coeff": 0.2, "zdim": 14, "test_results": {"test": {"acc": 0.75, "DP": 0.0, "EO": 0.0, "CF": 0.0}}}, {"fair_coeff": 0.2, "zdim": 15, "test_results": {"test": {"acc": 0.75, "DP": 0.0, "EO": 0.0, "CF": 0.0}}}, {"fair_coeff": 0.2, "zdim": 16, "test_results": {"test": {"acc": 0.75, "DP": 0.0, "EO": 0.0, "CF": 0.0}}}, {"fair_coeff": 0.2, "zdim": 17, "test_results": {"test": {"acc": 0.75, "DP": 0.0, "EO": 0.0, "CF": 0.0}}}, {"fair_coeff": 0.2, "zdim": 18, "test_results": {"test": {"acc": 0.75, "DP": 0.0, "EO": 0.0, "CF": 0.0}}}, {"fair_coeff": 0.2, "zdim": 19, "test_results": {"test": {"acc": 0.75, "DP": 0.0, "EO": 0.0, "CF": 0.0}}}, {"fair_coeff": 0.2, "zdim": 20, "test_results": {"test": {"acc": 0.75, "DP": 0.0, "EO": 0.0, "CF": 0.0}}}, {"fair_coeff": 0.3, "zdim": 6, "test_results": {"test": {"acc": 0.75, "DP": 0.0, "EO": 0.0, "CF": 0.0}}}, {"fair_coeff": 0.3, "zdim": 7, "test_results": {"test": {"acc": 0.75, "DP": 0.0, "EO": 0.0, "CF": 0.0}}}, {"fair_coeff": 0.3, "zdim": 8, "test_results": {"test": {"acc": 0.75, "DP": 0.0, "EO": 0.0, "CF": 0.0}}}, {"fair_coeff": 0.3, "zdim": 9, "test_results": {"test": {"acc": 0.75, "DP": 0.0, "EO": 0.0, "CF": 0.0}}}, {"fair_coeff": 0.3, "zdim": 10, "test_results": {"test": {"acc": 0.75, "DP": 0.0, "EO": 0.0, "CF": 0.0}}}, {"fair_coeff": 0.3, "zdim": 11, "test_results": {"test": {"acc": 0.75, "DP": 0.0, "EO": 0.0, "CF": 0.0}}}, {"fair_coeff": 0.3, "zdim": 12, "test_results": {"test": {"acc": 0.75, "DP": 0.0, "EO": 0.0, "CF": 0.0}}}, {"fair_coeff": 0.3, "zdim": 13, "test_results": {"test": {"acc": 0.75, "DP": 0.0, "EO": 0.0, "CF": 0.0}}}, {"fair_coeff": 0.3, "zdim": 14, "test_results": {"test": {"acc": 0.75, "DP": 0.0, "EO": 0.0, "CF": 0.0}}}, {"fair_coeff": 0.3, "zdim": 15, "test_results": {"test": {"acc": 0.75, "DP": 0.0, "EO": 0.0, "CF": 0.0}}}, {"fair_coeff": 0.3, "zdim": 16, "test_results": {"test": {"acc": 0.75, "DP": 0.0, "EO": 0.0, "CF": 0.0}}}, {"fair_coeff": 0.3, "zdim": 17, "test_results": {"test": {"acc": 0.75, "DP": 0.0, "EO": 0.0, "CF": 0.0}}}, {"fair_coeff": 0.3, "zdim": 18, "test_results": {"test": {"acc": 0.75, "DP": 0.0, "EO": 0.0, "CF": 0.0}}}, {"fair_coeff": 0.3, "zdim": 19, "test_results": {"test": {"acc": 0.75, "DP": 0.0, "EO": 0.0, "CF": 0.0}}}, {"fair_coeff": 0.3, "zdim": 20, "test_results": {"test": {"acc": 0.75, "DP": 0.0, "EO": 0.0, "CF": 0.0}}}, {"fair_coeff": 0.4, "zdim": 6, "test_results": {"test": {"acc": 0.75, "DP": 0.0, "EO": 0.0, "CF": 0.0}}}, {"fair_coeff": 0.4, "zdim": 7, "test_results": {"test": {"acc": 0.75, "DP": 0.0, "EO": 0.0, "CF": 0.0}}}, {"fair_coeff": 0.4, "zdim": 8, "test_results": {"test": {"acc": 0.75, "DP": 0.0, "EO": 0.0, "CF": 0.0}}}, {"fair_coeff": 0.4, "zdim": 9, "test_results": {"test": {"acc": 0.75, "DP": 0.0, "EO": 0.0, "CF": 0.0}}}, {"fair_coeff": 0.4, "zdim": 10, "test_results": {"test": {"acc": 0.75, "DP": 0.0, "EO": 0.0, "CF": 0.0}}}, {"fair_coeff": 0.4, "zdim": 11, "test_results": {"test": {"acc": 0.75, "DP": 0.0, "EO": 0.0, "CF": 0.0}}}, {"fair_coeff": 0.4, "zdim": 12, "test_results": {"test": {"acc": 0.75, "DP": 0.0, "EO": 0.0, "CF": 0.0}}}, {"fair_coeff": 0.4, "zdim": 13, "test_results": {"test": {"acc": 0.75, "DP": 0.0, "EO": 0.0, "CF": 0.0}}}, {"fair_coeff": 0.4, "zdim": 14, "test_results": {"test": {"acc": 0.75, "DP": 0.0, "EO": 0.0, "CF": 0.0}}}, {"fair_coeff": 0.4, "zdim": 15, "test_results": {"test": {"acc": 0.75, "DP": 0.0, "EO": 0.0, "CF": 0.0}}}, {"fair_coeff": 0.4, "zdim": 16, "test_results": {"test": {"acc": 0.75, "DP": 0.0, "EO": 0.0, "CF": 0.0}}}, {"fair_coeff": 0.4, "zdim": 17, "test_results": {"test": {"acc": 0.75, "DP": 0.0, "EO": 0.0, "CF": 0.0}}}, {"fair_coeff": 0.4, "zdim": 18, "test_results": {"test": {"acc": 0.75, "DP": 0.0, "EO": 0.0, "CF": 0.0}}}, {"fair_coeff": 0.4, "zdim": 19, "test_results": {"test": {"acc": 0.75, "DP": 0.0, "EO": 0.0, "CF": 0.0}}}, {"fair_coeff": 0.4, "zdim": 20, "test_results": {"test": {"acc": 0.75, "DP": 0.0, "EO": 0.0, "CF": 0.0}}}, {"fair_coeff": 0.5, "zdim": 6, "test_results": {"test": {"acc": 0.8450704225352113, "DP": 0.10661662496524882, "EO": 0.08506847183317776, "CF": 0.06798289738430584}}}, {"fair_coeff": 0.5, "zdim": 7, "test_results": {"test": {"acc": 0.8450704225352113, "DP": 0.10661662496524882, "EO": 0.08506847183317776, "CF": 0.06798289738430584}}}, {"fair_coeff": 0.5, "zdim": 8, "test_results": {"test": {"acc": 0.8450704225352113, "DP": 0.10661662496524882, "EO": 0.08506847183317776, "CF": 0.06798289738430584}}}, {"fair_coeff": 0.5, "zdim": 9, "test_results": {"test": {"acc": 0.8450704225352113, "DP": 0.10661662496524882, "EO": 0.08506847183317776, "CF": 0.06798289738430584}}}, {"fair_coeff": 0.5, "zdim": 10, "test_results": {"test": {"acc": 0.8450704225352113, "DP": 0.10661662496524882, "EO": 0.08506847183317776, "CF": 0.06798289738430584}}}, {"fair_coeff": 0.5, "zdim": 11, "test_results": {"test": {"acc": 0.8450704225352113, "DP": 0.10661662496524882, "EO": 0.08506847183317776, "CF": 0.06798289738430584}}}, {"fair_coeff": 0.5, "zdim": 12, "test_results": {"test": {"acc": 0.8450704225352113, "DP": 0.10661662496524882, "EO": 0.08506847183317776, "CF": 0.06798289738430584}}}, {"fair_coeff": 0.5, "zdim": 13, "test_results": {"test": {"acc": 0.8450704225352113, "DP": 0.10661662496524882, "EO": 0.08506847183317776, "CF": 0.06798289738430584}}}, {"fair_coeff": 0.5, "zdim": 14, "test_results": {"test": {"acc": 0.8450704225352113, "DP": 0.10661662496524882, "EO": 0.08506847183317776, "CF": 0.06798289738430584}}}, {"fair_coeff": 0.5, "zdim": 15, "test_results": {"test": {"acc": 0.8450704225352113, "DP": 0.10661662496524882, "EO": 0.08506847183317776, "CF": 0.06798289738430584}}}, {"fair_coeff": 0.5, "zdim": 16, "test_results": {"test": {"acc": 0.8450704225352113, "DP": 0.10661662496524882, "EO": 0.08506847183317776, "CF": 0.06798289738430584}}}, {"fair_coeff": 0.5, "zdim": 17, "test_results": {"test": {"acc": 0.8450704225352113, "DP": 0.10661662496524882, "EO": 0.08506847183317776, "CF": 0.06798289738430584}}}, {"fair_coeff": 0.5, "zdim": 18, "test_results": {"test": {"acc": 0.8450704225352113, "DP": 0.10661662496524882, "EO": 0.08506847183317776, "CF": 0.06798289738430584}}}, {"fair_coeff": 0.5, "zdim": 19, "test_results": {"test": {"acc": 0.8450704225352113, "DP": 0.10661662496524882, "EO": 0.08506847183317776, "CF": 0.06798289738430584}}}, {"fair_coeff": 0.5, "zdim": 20, "test_results": {"test": {"acc": 0.8450704225352113, "DP": 0.10661662496524882, "EO": 0.08506847183317776, "CF": 0.06798289738430584}}}, {"fair_coeff": 0.6, "zdim": 6, "test_results": {"test": {"acc": 0.75, "DP": 0.0, "EO": 0.0, "CF": 0.0}}}, {"fair_coeff": 0.6, "zdim": 7, "test_results": {"test": {"acc": 0.75, "DP": 0.0, "EO": 0.0, "CF": 0.0}}}, {"fair_coeff": 0.6, "zdim": 8, "test_results": {"test": {"acc": 0.75, "DP": 0.0, "EO": 0.0, "CF": 0.0}}}, {"fair_coeff": 0.6, "zdim": 9, "test_results": {"test": {"acc": 0.75, "DP": 0.0, "EO": 0.0, "CF": 0.0}}}, {"fair_coeff": 0.6, "zdim": 10, "test_results": {"test": {"acc": 0.75, "DP": 0.0, "EO": 0.0, "CF": 0.0}}}, {"fair_coeff": 0.6, "zdim": 11, "test_results": {"test": {"acc": 0.75, "DP": 0.0, "EO": 0.0, "CF": 0.0}}}, {"fair_coeff": 0.6, "zdim": 12, "test_results": {"test": {"acc": 0.75, "DP": 0.0, "EO": 0.0, "CF": 0.0}}}, {"fair_coeff": 0.6, "zdim": 13, "test_results": {"test": {"acc": 0.75, "DP": 0.0, "EO": 0.0, "CF": 0.0}}}, {"fair_coeff": 0.6, "zdim": 14, "test_results": {"test": {"acc": 0.75, "DP": 0.0, "EO": 0.0, "CF": 0.0}}}, {"fair_coeff": 0.6, "zdim": 15, "test_results": {"test": {"acc": 0.75, "DP": 0.0, "EO": 0.0, "CF": 0.0}}}, {"fair_coeff": 0.6, "zdim": 16, "test_results": {"test": {"acc": 0.75, "DP": 0.0, "EO": 0.0, "CF": 0.0}}}, {"fair_coeff": 0.6, "zdim": 17, "test_results": {"test": {"acc": 0.75, "DP": 0.0, "EO": 0.0, "CF": 0.0}}}, {"fair_coeff": 0.6, "zdim": 18, "test_results": {"test": {"acc": 0.75, "DP": 0.0, "EO": 0.0, "CF": 0.0}}}, {"fair_coeff": 0.6, "zdim": 19, "test_results": {"test": {"acc": 0.75, "DP": 0.0, "EO": 0.0, "CF": 0.0}}}, {"fair_coeff": 0.6, "zdim": 20, "test_results": {"test": {"acc": 0.75, "DP": 0.0, "EO": 0.0, "CF": 0.0}}}, {"fair_coeff": 0.7, "zdim": 6, "test_results": {"test": {"acc": 0.8591549295774648, "DP": 0.1291353906032805, "EO": 0.10757858699035167, "CF": 0.07599974849094568}}}, {"fair_coeff": 0.7, "zdim": 7, "test_results": {"test": {"acc": 0.8591549295774648, "DP": 0.1291353906032805, "EO": 0.10757858699035167, "CF": 0.07599974849094568}}}, {"fair_coeff": 0.7, "zdim": 8, "test_results": {"test": {"acc": 0.8591549295774648, "DP": 0.1291353906032805, "EO": 0.10757858699035167, "CF": 0.07599974849094568}}}, {"fair_coeff": 0.7, "zdim": 9, "test_results": {"test": {"acc": 0.8591549295774648, "DP": 0.1291353906032805, "EO": 0.10757858699035167, "CF": 0.07599974849094568}}}, {"fair_coeff": 0.7, "zdim": 10, "test_results": {"test": {"acc": 0.8591549295774648, "DP": 0.1291353906032805, "EO": 0.10757858699035167, "CF": 0.07599974849094568}}}, {"fair_coeff": 0.7, "zdim": 11, "test_results": {"test": {"acc": 0.8591549295774648, "DP": 0.1291353906032805, "EO": 0.10757858699035167, "CF": 0.07599974849094568}}}, {"fair_coeff": 0.7, "zdim": 12, "test_results": {"test": {"acc": 0.8591549295774648, "DP": 0.1291353906032805, "EO": 0.10757858699035167, "CF": 0.07599974849094568}}}, {"fair_coeff": 0.7, "zdim": 13, "test_results": {"test": {"acc": 0.8591549295774648, "DP": 0.1291353906032805, "EO": 0.10757858699035167, "CF": 0.07599974849094568}}}, {"fair_coeff": 0.7, "zdim": 14, "test_results": {"test": {"acc": 0.8591549295774648, "DP": 0.1291353906032805, "EO": 0.10757858699035167, "CF": 0.07599974849094568}}}, {"fair_coeff": 0.7, "zdim": 15, "test_results": {"test": {"acc": 0.8591549295774648, "DP": 0.1291353906032805, "EO": 0.10757858699035167, "CF": 0.07599974849094568}}}, {"fair_coeff": 0.7, "zdim": 16, "test_results": {"test": {"acc": 0.8591549295774648, "DP": 0.1291353906032805, "EO": 0.10757858699035167, "CF": 0.07599974849094568}}}, {"fair_coeff": 0.7, "zdim": 17, "test_results": {"test": {"acc": 0.8591549295774648, "DP": 0.1291353906032805, "EO": 0.10757858699035167, "CF": 0.07599974849094568}}}, {"fair_coeff": 0.7, "zdim": 18, "test_results": {"test": {"acc": 0.8591549295774648, "DP": 0.1291353906032805, "EO": 0.10757858699035167, "CF": 0.07599974849094568}}}, {"fair_coeff": 0.7, "zdim": 19, "test_results": {"test": {"acc": 0.8591549295774648, "DP": 0.1291353906032805, "EO": 0.10757858699035167, "CF": 0.07599974849094568}}}, {"fair_coeff": 0.7, "zdim": 20, "test_results": {"test": {"acc": 0.8591549295774648, "DP": 0.1291353906032805, "EO": 0.10757858699035167, "CF": 0.07599974849094568}}}, {"fair_coeff": 0.8, "zdim": 6, "test_results": {"test": {"acc": 0.75, "DP": 0.0, "EO": 0.0, "CF": 0.0}}}, {"fair_coeff": 0.8, "zdim": 7, "test_results": {"test": {"acc": 0.75, "DP": 0.0, "EO": 0.0, "CF": 0.0}}}, {"fair_coeff": 0.8, "zdim": 8, "test_results": {"test": {"acc": 0.75, "DP": 0.0, "EO": 0.0, "CF": 0.0}}}, {"fair_coeff": 0.8, "zdim": 9, "test_results": {"test": {"acc": 0.75, "DP": 0.0, "EO": 0.0, "CF": 0.0}}}, {"fair_coeff": 0.8, "zdim": 10, "test_results": {"test": {"acc": 0.75, "DP": 0.0, "EO": 0.0, "CF": 0.0}}}, {"fair_coeff": 0.8, "zdim": 11, "test_results": {"test": {"acc": 0.75, "DP": 0.0, "EO": 0.0, "CF": 0.0}}}, {"fair_coeff": 0.8, "zdim": 12, "test_results": {"test": {"acc": 0.75, "DP": 0.0, "EO": 0.0, "CF": 0.0}}}, {"fair_coeff": 0.8, "zdim": 13, "test_results": {"test": {"acc": 0.75, "DP": 0.0, "EO": 0.0, "CF": 0.0}}}, {"fair_coeff": 0.8, "zdim": 14, "test_results": {"test": {"acc": 0.75, "DP": 0.0, "EO": 0.0, "CF": 0.0}}}, {"fair_coeff": 0.8, "zdim": 15, "test_results": {"test": {"acc": 0.75, "DP": 0.0, "EO": 0.0, "CF": 0.0}}}, {"fair_coeff": 0.8, "zdim": 16, "test_results": {"test": {"acc": 0.75, "DP": 0.0, "EO": 0.0, "CF": 0.0}}}, {"fair_coeff": 0.8, "zdim": 17, "test_results": {"test": {"acc": 0.75, "DP": 0.0, "EO": 0.0, "CF": 0.0}}}, {"fair_coeff": 0.8, "zdim": 18, "test_results": {"test": {"acc": 0.75, "DP": 0.0, "EO": 0.0, "CF": 0.0}}}, {"fair_coeff": 0.8, "zdim": 19, "test_results": {"test": {"acc": 0.75, "DP": 0.0, "EO": 0.0, "CF": 0.0}}}, {"fair_coeff": 0.8, "zdim": 20, "test_results": {"test": {"acc": 0.75, "DP": 0.0, "EO": 0.0, "CF": 0.0}}}, {"fair_coeff": 0.9, "zdim": 6, "test_results": {"test": {"acc": 0.75, "DP": 0.0, "EO": 0.0, "CF": 0.0}}}, {"fair_coeff": 0.9, "zdim": 7, "test_results": {"test": {"acc": 0.75, "DP": 0.0, "EO": 0.0, "CF": 0.0}}}, {"fair_coeff": 0.9, "zdim": 8, "test_results": {"test": {"acc": 0.75, "DP": 0.0, "EO": 0.0, "CF": 0.0}}}, {"fair_coeff": 0.9, "zdim": 9, "test_results": {"test": {"acc": 0.75, "DP": 0.0, "EO": 0.0, "CF": 0.0}}}, {"fair_coeff": 0.9, "zdim": 10, "test_results": {"test": {"acc": 0.75, "DP": 0.0, "EO": 0.0, "CF": 0.0}}}, {"fair_coeff": 0.9, "zdim": 11, "test_results": {"test": {"acc": 0.75, "DP": 0.0, "EO": 0.0, "CF": 0.0}}}, {"fair_coeff": 0.9, "zdim": 12, "test_results": {"test": {"acc": 0.75, "DP": 0.0, "EO": 0.0, "CF": 0.0}}}, {"fair_coeff": 0.9, "zdim": 13, "test_results": {"test": {"acc": 0.75, "DP": 0.0, "EO": 0.0, "CF": 0.0}}}, {"fair_coeff": 0.9, "zdim": 14, "test_results": {"test": {"acc": 0.75, "DP": 0.0, "EO": 0.0, "CF": 0.0}}}, {"fair_coeff": 0.9, "zdim": 15, "test_results": {"test": {"acc": 0.75, "DP": 0.0, "EO": 0.0, "CF": 0.0}}}, {"fair_coeff": 0.9, "zdim": 16, "test_results": {"test": {"acc": 0.75, "DP": 0.0, "EO": 0.0, "CF": 0.0}}}, {"fair_coeff": 0.9, "zdim": 17, "test_results": {"test": {"acc": 0.75, "DP": 0.0, "EO": 0.0, "CF": 0.0}}}, {"fair_coeff": 0.9, "zdim": 18, "test_results": {"test": {"acc": 0.75, "DP": 0.0, "EO": 0.0, "CF": 0.0}}}, {"fair_coeff": 0.9, "zdim": 19, "test_results": {"test": {"acc": 0.75, "DP": 0.0, "EO": 0.0, "CF": 0.0}}}, {"fair_coeff": 0.9, "zdim": 20, "test_results": {"test": {"acc": 0.75, "DP": 0.0, "EO": 0.0, "CF": 0.0}}}, {"fair_coeff": 1.0, "zdim": 6, "test_results": {"test": {"acc": 0.8626760563380281, "DP": 0.11676396997497915, "EO": 0.09679816370992841, "CF": 0.056438631790744466}}}, {"fair_coeff": 1.0, "zdim": 7, "test_results": {"test": {"acc": 0.8626760563380281, "DP": 0.11676396997497915, "EO": 0.09679816370992841, "CF": 0.056438631790744466}}}, {"fair_coeff": 1.0, "zdim": 8, "test_results": {"test": {"acc": 0.8626760563380281, "DP": 0.11676396997497915, "EO": 0.09679816370992841, "CF": 0.056438631790744466}}}, {"fair_coeff": 1.0, "zdim": 9, "test_results": {"test": {"acc": 0.8626760563380281, "DP": 0.11676396997497915, "EO": 0.09679816370992841, "CF": 0.056438631790744466}}}, {"fair_coeff": 1.0, "zdim": 10, "test_results": {"test": {"acc": 0.8626760563380281, "DP": 0.11676396997497915, "EO": 0.09679816370992841, "CF": 0.056438631790744466}}}, {"fair_coeff": 1.0, "zdim": 11, "test_results": {"test": {"acc": 0.8626760563380281, "DP": 0.11676396997497915, "EO": 0.09679816370992841, "CF": 0.056438631790744466}}}, {"fair_coeff": 1.0, "zdim": 12, "test_results": {"test": {"acc": 0.8626760563380281, "DP": 0.11676396997497915, "EO": 0.09679816370992841, "CF": 0.056438631790744466}}}, {"fair_coeff": 1.0, "zdim": 13, "test_results": {"test": {"acc": 0.8626760563380281, "DP": 0.11676396997497915, "EO": 0.09679816370992841, "CF": 0.056438631790744466}}}, {"fair_coeff": 1.0, "zdim": 14, "test_results": {"test": {"acc": 0.8626760563380281, "DP": 0.11676396997497915, "EO": 0.09679816370992841, "CF": 0.056438631790744466}}}, {"fair_coeff": 1.0, "zdim": 15, "test_results": {"test": {"acc": 0.8626760563380281, "DP": 0.11676396997497915, "EO": 0.09679816370992841, "CF": 0.056438631790744466}}}, {"fair_coeff": 1.0, "zdim": 16, "test_results": {"test": {"acc": 0.8626760563380281, "DP": 0.11676396997497915, "EO": 0.09679816370992841, "CF": 0.056438631790744466}}}, {"fair_coeff": 1.0, "zdim": 17, "test_results": {"test": {"acc": 0.8626760563380281, "DP": 0.11676396997497915, "EO": 0.09679816370992841, "CF": 0.056438631790744466}}}, {"fair_coeff": 1.0, "zdim": 18, "test_results": {"test": {"acc": 0.8626760563380281, "DP": 0.11676396997497915, "EO": 0.09679816370992841, "CF": 0.056438631790744466}}}, {"fair_coeff": 1.0, "zdim": 19, "test_results": {"test": {"acc": 0.8626760563380281, "DP": 0.11676396997497915, "EO": 0.09679816370992841, "CF": 0.056438631790744466}}}, {"fair_coeff": 1.0, "zdim": 20, "test_results": {"test": {"acc": 0.8626760563380281, "DP": 0.11676396997497915, "EO": 0.09679816370992841, "CF": 0.056438631790744466}}}, {"fair_coeff": 2.0, "zdim": 6, "test_results": {"test": {"acc": 0.852112676056338, "DP": 0.11996107867667499, "EO": 0.09865001556178024, "CF": 0.06573817907444668}}}, {"fair_coeff": 2.0, "zdim": 7, "test_results": {"test": {"acc": 0.852112676056338, "DP": 0.11996107867667499, "EO": 0.09865001556178024, "CF": 0.06573817907444668}}}, {"fair_coeff": 2.0, "zdim": 8, "test_results": {"test": {"acc": 0.852112676056338, "DP": 0.11996107867667499, "EO": 0.09865001556178024, "CF": 0.06573817907444668}}}, {"fair_coeff": 2.0, "zdim": 9, "test_results": {"test": {"acc": 0.852112676056338, "DP": 0.11996107867667499, "EO": 0.09865001556178024, "CF": 0.06573817907444668}}}, {"fair_coeff": 2.0, "zdim": 10, "test_results": {"test": {"acc": 0.852112676056338, "DP": 0.11996107867667499, "EO": 0.09865001556178024, "CF": 0.06573817907444668}}}, {"fair_coeff": 2.0, "zdim": 11, "test_results": {"test": {"acc": 0.852112676056338, "DP": 0.11996107867667499, "EO": 0.09865001556178024, "CF": 0.06573817907444668}}}, {"fair_coeff": 2.0, "zdim": 12, "test_results": {"test": {"acc": 0.852112676056338, "DP": 0.11996107867667499, "EO": 0.09865001556178024, "CF": 0.06573817907444668}}}, {"fair_coeff": 2.0, "zdim": 13, "test_results": {"test": {"acc": 0.852112676056338, "DP": 0.11996107867667499, "EO": 0.09865001556178024, "CF": 0.06573817907444668}}}, {"fair_coeff": 2.0, "zdim": 14, "test_results": {"test": {"acc": 0.852112676056338, "DP": 0.11996107867667499, "EO": 0.09865001556178024, "CF": 0.06573817907444668}}}, {"fair_coeff": 2.0, "zdim": 15, "test_results": {"test": {"acc": 0.852112676056338, "DP": 0.11996107867667499, "EO": 0.09865001556178024, "CF": 0.06573817907444668}}}, {"fair_coeff": 2.0, "zdim": 16, "test_results": {"test": {"acc": 0.852112676056338, "DP": 0.11996107867667499, "EO": 0.09865001556178024, "CF": 0.06573817907444668}}}, {"fair_coeff": 2.0, "zdim": 17, "test_results": {"test": {"acc": 0.852112676056338, "DP": 0.11996107867667499, "EO": 0.09865001556178024, "CF": 0.06573817907444668}}}, {"fair_coeff": 2.0, "zdim": 18, "test_results": {"test": {"acc": 0.852112676056338, "DP": 0.11996107867667499, "EO": 0.09865001556178024, "CF": 0.06573817907444668}}}, {"fair_coeff": 2.0, "zdim": 19, "test_results": {"test": {"acc": 0.852112676056338, "DP": 0.11996107867667499, "EO": 0.09865001556178024, "CF": 0.06573817907444668}}}, {"fair_coeff": 2.0, "zdim": 20, "test_results": {"test": {"acc": 0.852112676056338, "DP": 0.11996107867667499, "EO": 0.09865001556178024, "CF": 0.06573817907444668}}}, {"fair_coeff": 3.0, "zdim": 6, "test_results": {"test": {"acc": 0.8697183098591549, "DP": 0.09702529886016126, "EO": 0.07550186741363207, "CF": 0.04008425553319919}}}, {"fair_coeff": 3.0, "zdim": 7, "test_results": {"test": {"acc": 0.8697183098591549, "DP": 0.09702529886016126, "EO": 0.07550186741363207, "CF": 0.04008425553319919}}}, {"fair_coeff": 3.0, "zdim": 8, "test_results": {"test": {"acc": 0.8697183098591549, "DP": 0.09702529886016126, "EO": 0.07550186741363207, "CF": 0.04008425553319919}}}, {"fair_coeff": 3.0, "zdim": 9, "test_results": {"test": {"acc": 0.8697183098591549, "DP": 0.09702529886016126, "EO": 0.07550186741363207, "CF": 0.04008425553319919}}}, {"fair_coeff": 3.0, "zdim": 10, "test_results": {"test": {"acc": 0.8697183098591549, "DP": 0.09702529886016126, "EO": 0.07550186741363207, "CF": 0.04008425553319919}}}, {"fair_coeff": 3.0, "zdim": 11, "test_results": {"test": {"acc": 0.8697183098591549, "DP": 0.09702529886016126, "EO": 0.07550186741363207, "CF": 0.04008425553319919}}}, {"fair_coeff": 3.0, "zdim": 12, "test_results": {"test": {"acc": 0.8697183098591549, "DP": 0.09702529886016126, "EO": 0.07550186741363207, "CF": 0.04008425553319919}}}, {"fair_coeff": 3.0, "zdim": 13, "test_results": {"test": {"acc": 0.8697183098591549, "DP": 0.09702529886016126, "EO": 0.07550186741363207, "CF": 0.04008425553319919}}}, {"fair_coeff": 3.0, "zdim": 14, "test_results": {"test": {"acc": 0.8697183098591549, "DP": 0.09702529886016126, "EO": 0.07550186741363207, "CF": 0.04008425553319919}}}, {"fair_coeff": 3.0, "zdim": 15, "test_results": {"test": {"acc": 0.8697183098591549, "DP": 0.09702529886016126, "EO": 0.07550186741363207, "CF": 0.04008425553319919}}}, {"fair_coeff": 3.0, "zdim": 16, "test_results": {"test": {"acc": 0.8697183098591549, "DP": 0.09702529886016126, "EO": 0.07550186741363207, "CF": 0.04008425553319919}}}, {"fair_coeff": 3.0, "zdim": 17, "test_results": {"test": {"acc": 0.8697183098591549, "DP": 0.09702529886016126, "EO": 0.07550186741363207, "CF": 0.04008425553319919}}}, {"fair_coeff": 3.0, "zdim": 18, "test_results": {"test": {"acc": 0.8697183098591549, "DP": 0.09702529886016126, "EO": 0.07550186741363207, "CF": 0.04008425553319919}}}, {"fair_coeff": 3.0, "zdim": 19, "test_results": {"test": {"acc": 0.8697183098591549, "DP": 0.09702529886016126, "EO": 0.07550186741363207, "CF": 0.04008425553319919}}}, {"fair_coeff": 3.0, "zdim": 20, "test_results": {"test": {"acc": 0.8697183098591549, "DP": 0.09702529886016126, "EO": 0.07550186741363207, "CF": 0.04008425553319919}}}, {"fair_coeff": 4.0, "zdim": 6, "test_results": {"test": {"acc": 0.8661971830985915, "DP": 0.11078676675006949, "EO": 0.08922541238717707, "CF": 0.05547660965794769}}}, {"fair_coeff": 4.0, "zdim": 7, "test_results": {"test": {"acc": 0.8661971830985915, "DP": 0.11078676675006949, "EO": 0.08922541238717707, "CF": 0.05547660965794769}}}, {"fair_coeff": 4.0, "zdim": 8, "test_results": {"test": {"acc": 0.8661971830985915, "DP": 0.11078676675006949, "EO": 0.08922541238717707, "CF": 0.05547660965794769}}}, {"fair_coeff": 4.0, "zdim": 9, "test_results": {"test": {"acc": 0.8661971830985915, "DP": 0.11078676675006949, "EO": 0.08922541238717707, "CF": 0.05547660965794769}}}, {"fair_coeff": 4.0, "zdim": 10, "test_results": {"test": {"acc": 0.8661971830985915, "DP": 0.11078676675006949, "EO": 0.08922541238717707, "CF": 0.05547660965794769}}}, {"fair_coeff": 4.0, "zdim": 11, "test_results": {"test": {"acc": 0.8661971830985915, "DP": 0.11078676675006949, "EO": 0.08922541238717707, "CF": 0.05547660965794769}}}, {"fair_coeff": 4.0, "zdim": 12, "test_results": {"test": {"acc": 0.8661971830985915, "DP": 0.11078676675006949, "EO": 0.08922541238717707, "CF": 0.05547660965794769}}}, {"fair_coeff": 4.0, "zdim": 13, "test_results": {"test": {"acc": 0.8661971830985915, "DP": 0.11078676675006949, "EO": 0.08922541238717707, "CF": 0.05547660965794769}}}, {"fair_coeff": 4.0, "zdim": 14, "test_results": {"test": {"acc": 0.8661971830985915, "DP": 0.11078676675006949, "EO": 0.08922541238717707, "CF": 0.05547660965794769}}}, {"fair_coeff": 4.0, "zdim": 15, "test_results": {"test": {"acc": 0.8661971830985915, "DP": 0.11078676675006949, "EO": 0.08922541238717707, "CF": 0.05547660965794769}}}, {"fair_coeff": 4.0, "zdim": 16, "test_results": {"test": {"acc": 0.8661971830985915, "DP": 0.11078676675006949, "EO": 0.08922541238717707, "CF": 0.05547660965794769}}}, {"fair_coeff": 4.0, "zdim": 17, "test_results": {"test": {"acc": 0.8661971830985915, "DP": 0.11078676675006949, "EO": 0.08922541238717707, "CF": 0.05547660965794769}}}, {"fair_coeff": 4.0, "zdim": 18, "test_results": {"test": {"acc": 0.8661971830985915, "DP": 0.11078676675006949, "EO": 0.08922541238717707, "CF": 0.05547660965794769}}}, {"fair_coeff": 4.0, "zdim": 19, "test_results": {"test": {"acc": 0.8661971830985915, "DP": 0.11078676675006949, "EO": 0.08922541238717707, "CF": 0.05547660965794769}}}, {"fair_coeff": 4.0, "zdim": 20, "test_results": {"test": {"acc": 0.8661971830985915, "DP": 0.11078676675006949, "EO": 0.08922541238717707, "CF": 0.05547660965794769}}}, {"fair_coeff": 5.0, "zdim": 6, "test_results": {"test": {"acc": 0.8556338028169014, "DP": 0.12593828190158465, "EO": 0.10605742296918763, "CF": 0.06670020120724347}}}, {"fair_coeff": 5.0, "zdim": 7, "test_results": {"test": {"acc": 0.8556338028169014, "DP": 0.12593828190158465, "EO": 0.10605742296918763, "CF": 0.06670020120724347}}}, {"fair_coeff": 5.0, "zdim": 8, "test_results": {"test": {"acc": 0.8556338028169014, "DP": 0.12593828190158465, "EO": 0.10605742296918763, "CF": 0.06670020120724347}}}, {"fair_coeff": 5.0, "zdim": 9, "test_results": {"test": {"acc": 0.8556338028169014, "DP": 0.12593828190158465, "EO": 0.10605742296918763, "CF": 0.06670020120724347}}}, {"fair_coeff": 5.0, "zdim": 10, "test_results": {"test": {"acc": 0.8556338028169014, "DP": 0.12593828190158465, "EO": 0.10605742296918763, "CF": 0.06670020120724347}}}, {"fair_coeff": 5.0, "zdim": 11, "test_results": {"test": {"acc": 0.8556338028169014, "DP": 0.12593828190158465, "EO": 0.10605742296918763, "CF": 0.06670020120724347}}}, {"fair_coeff": 5.0, "zdim": 12, "test_results": {"test": {"acc": 0.8556338028169014, "DP": 0.12593828190158465, "EO": 0.10605742296918763, "CF": 0.06670020120724347}}}, {"fair_coeff": 5.0, "zdim": 13, "test_results": {"test": {"acc": 0.8556338028169014, "DP": 0.12593828190158465, "EO": 0.10605742296918763, "CF": 0.06670020120724347}}}, {"fair_coeff": 5.0, "zdim": 14, "test_results": {"test": {"acc": 0.8556338028169014, "DP": 0.12593828190158465, "EO": 0.10605742296918763, "CF": 0.06670020120724347}}}, {"fair_coeff": 5.0, "zdim": 15, "test_results": {"test": {"acc": 0.8556338028169014, "DP": 0.12593828190158465, "EO": 0.10605742296918763, "CF": 0.06670020120724347}}}, {"fair_coeff": 5.0, "zdim": 16, "test_results": {"test": {"acc": 0.8556338028169014, "DP": 0.12593828190158465, "EO": 0.10605742296918763, "CF": 0.06670020120724347}}}, {"fair_coeff": 5.0, "zdim": 17, "test_results": {"test": {"acc": 0.8556338028169014, "DP": 0.12593828190158465, "EO": 0.10605742296918763, "CF": 0.06670020120724347}}}, {"fair_coeff": 5.0, "zdim": 18, "test_results": {"test": {"acc": 0.8556338028169014, "DP": 0.12593828190158465, "EO": 0.10605742296918763, "CF": 0.06670020120724347}}}, {"fair_coeff": 5.0, "zdim": 19, "test_results": {"test": {"acc": 0.8556338028169014, "DP": 0.12593828190158465, "EO": 0.10605742296918763, "CF": 0.06670020120724347}}}, {"fair_coeff": 5.0, "zdim": 20, "test_results": {"test": {"acc": 0.8556338028169014, "DP": 0.12593828190158465, "EO": 0.10605742296918763, "CF": 0.06670020120724347}}}, {"fair_coeff": 6.0, "zdim": 6, "test_results": {"test": {"acc": 0.8802816901408451, "DP": 0.06130108423686406, "EO": 0.04430827886710237, "CF": 0.010587618325724048}}}, {"fair_coeff": 6.0, "zdim": 7, "test_results": {"test": {"acc": 0.8802816901408451, "DP": 0.06130108423686406, "EO": 0.04430827886710237, "CF": 0.010587618325724048}}}, {"fair_coeff": 6.0, "zdim": 8, "test_results": {"test": {"acc": 0.8802816901408451, "DP": 0.06130108423686406, "EO": 0.04430827886710237, "CF": 0.010587618325724048}}}, {"fair_coeff": 6.0, "zdim": 9, "test_results": {"test": {"acc": 0.8802816901408451, "DP": 0.06130108423686406, "EO": 0.04430827886710237, "CF": 0.010587618325724048}}}, {"fair_coeff": 6.0, "zdim": 10, "test_results": {"test": {"acc": 0.8802816901408451, "DP": 0.06130108423686406, "EO": 0.04430827886710237, "CF": 0.010587618325724048}}}, {"fair_coeff": 6.0, "zdim": 11, "test_results": {"test": {"acc": 0.8802816901408451, "DP": 0.06130108423686406, "EO": 0.04430827886710237, "CF": 0.010587618325724048}}}, {"fair_coeff": 6.0, "zdim": 12, "test_results": {"test": {"acc": 0.8802816901408451, "DP": 0.06130108423686406, "EO": 0.04430827886710237, "CF": 0.010587618325724048}}}, {"fair_coeff": 6.0, "zdim": 13, "test_results": {"test": {"acc": 0.8802816901408451, "DP": 0.06130108423686406, "EO": 0.04430827886710237, "CF": 0.010587618325724048}}}, {"fair_coeff": 6.0, "zdim": 14, "test_results": {"test": {"acc": 0.8802816901408451, "DP": 0.06130108423686406, "EO": 0.04430827886710237, "CF": 0.010587618325724048}}}, {"fair_coeff": 6.0, "zdim": 15, "test_results": {"test": {"acc": 0.8802816901408451, "DP": 0.06130108423686406, "EO": 0.04430827886710237, "CF": 0.010587618325724048}}}, {"fair_coeff": 6.0, "zdim": 16, "test_results": {"test": {"acc": 0.8802816901408451, "DP": 0.06130108423686406, "EO": 0.04430827886710237, "CF": 0.010587618325724048}}}, {"fair_coeff": 6.0, "zdim": 17, "test_results": {"test": {"acc": 0.8802816901408451, "DP": 0.06130108423686406, "EO": 0.04430827886710237, "CF": 0.010587618325724048}}}, {"fair_coeff": 6.0, "zdim": 18, "test_results": {"test": {"acc": 0.8802816901408451, "DP": 0.06130108423686406, "EO": 0.04430827886710237, "CF": 0.010587618325724048}}}, {"fair_coeff": 6.0, "zdim": 19, "test_results": {"test": {"acc": 0.8802816901408451, "DP": 0.06130108423686406, "EO": 0.04430827886710237, "CF": 0.010587618325724048}}}, {"fair_coeff": 6.0, "zdim": 20, "test_results": {"test": {"acc": 0.8802816901408451, "DP": 0.06130108423686406, "EO": 0.04430827886710237, "CF": 0.010587618325724048}}}, {"fair_coeff": 7.0, "zdim": 6, "test_results": {"test": {"acc": 0.8697183098591549, "DP": 0.10758965804837364, "EO": 0.08753890445066911, "CF": 0.04617706237424547}}}, {"fair_coeff": 7.0, "zdim": 7, "test_results": {"test": {"acc": 0.8697183098591549, "DP": 0.10758965804837364, "EO": 0.08753890445066911, "CF": 0.04617706237424547}}}, {"fair_coeff": 7.0, "zdim": 8, "test_results": {"test": {"acc": 0.8697183098591549, "DP": 0.10758965804837364, "EO": 0.08753890445066911, "CF": 0.04617706237424547}}}, {"fair_coeff": 7.0, "zdim": 9, "test_results": {"test": {"acc": 0.8697183098591549, "DP": 0.10758965804837364, "EO": 0.08753890445066911, "CF": 0.04617706237424547}}}, {"fair_coeff": 7.0, "zdim": 10, "test_results": {"test": {"acc": 0.8697183098591549, "DP": 0.10758965804837364, "EO": 0.08753890445066911, "CF": 0.04617706237424547}}}, {"fair_coeff": 7.0, "zdim": 11, "test_results": {"test": {"acc": 0.8697183098591549, "DP": 0.10758965804837364, "EO": 0.08753890445066911, "CF": 0.04617706237424547}}}, {"fair_coeff": 7.0, "zdim": 12, "test_results": {"test": {"acc": 0.8697183098591549, "DP": 0.10758965804837364, "EO": 0.08753890445066911, "CF": 0.04617706237424547}}}, {"fair_coeff": 7.0, "zdim": 13, "test_results": {"test": {"acc": 0.8697183098591549, "DP": 0.10758965804837364, "EO": 0.08753890445066911, "CF": 0.04617706237424547}}}, {"fair_coeff": 7.0, "zdim": 14, "test_results": {"test": {"acc": 0.8697183098591549, "DP": 0.10758965804837364, "EO": 0.08753890445066911, "CF": 0.04617706237424547}}}, {"fair_coeff": 7.0, "zdim": 15, "test_results": {"test": {"acc": 0.8697183098591549, "DP": 0.10758965804837364, "EO": 0.08753890445066911, "CF": 0.04617706237424547}}}, {"fair_coeff": 7.0, "zdim": 16, "test_results": {"test": {"acc": 0.8697183098591549, "DP": 0.10758965804837364, "EO": 0.08753890445066911, "CF": 0.04617706237424547}}}, {"fair_coeff": 7.0, "zdim": 17, "test_results": {"test": {"acc": 0.8697183098591549, "DP": 0.10758965804837364, "EO": 0.08753890445066911, "CF": 0.04617706237424547}}}, {"fair_coeff": 7.0, "zdim": 18, "test_results": {"test": {"acc": 0.8697183098591549, "DP": 0.10758965804837364, "EO": 0.08753890445066911, "CF": 0.04617706237424547}}}, {"fair_coeff": 7.0, "zdim": 19, "test_results": {"test": {"acc": 0.8697183098591549, "DP": 0.10758965804837364, "EO": 0.08753890445066911, "CF": 0.04617706237424547}}}, {"fair_coeff": 7.0, "zdim": 20, "test_results": {"test": {"acc": 0.8697183098591549, "DP": 0.10758965804837364, "EO": 0.08753890445066911, "CF": 0.04617706237424547}}}, {"fair_coeff": 8.0, "zdim": 6, "test_results": {"test": {"acc": 0.8661971830985915, "DP": 0.10300250208507092, "EO": 0.08307461873638339, "CF": 0.05059720022261228}}}, {"fair_coeff": 8.0, "zdim": 7, "test_results": {"test": {"acc": 0.8661971830985915, "DP": 0.10300250208507092, "EO": 0.08307461873638339, "CF": 0.05059720022261228}}}, {"fair_coeff": 8.0, "zdim": 8, "test_results": {"test": {"acc": 0.8661971830985915, "DP": 0.10300250208507092, "EO": 0.08307461873638339, "CF": 0.05059720022261228}}}, {"fair_coeff": 8.0, "zdim": 9, "test_results": {"test": {"acc": 0.8661971830985915, "DP": 0.10300250208507092, "EO": 0.08307461873638339, "CF": 0.05059720022261228}}}, {"fair_coeff": 8.0, "zdim": 10, "test_results": {"test": {"acc": 0.8661971830985915, "DP": 0.10300250208507092, "EO": 0.08307461873638339, "CF": 0.05059720022261228}}}, {"fair_coeff": 8.0, "zdim": 11, "test_results": {"test": {"acc": 0.8661971830985915, "DP": 0.10300250208507092, "EO": 0.08307461873638339, "CF": 0.05059720022261228}}}, {"fair_coeff": 8.0, "zdim": 12, "test_results": {"test": {"acc": 0.8661971830985915, "DP": 0.10300250208507092, "EO": 0.08307461873638339, "CF": 0.05059720022261228}}}, {"fair_coeff": 8.0, "zdim": 13, "test_results": {"test": {"acc": 0.8661971830985915, "DP": 0.10300250208507092, "EO": 0.08307461873638339, "CF": 0.05059720022261228}}}, {"fair_coeff": 8.0, "zdim": 14, "test_results": {"test": {"acc": 0.8661971830985915, "DP": 0.10300250208507092, "EO": 0.08307461873638339, "CF": 0.05059720022261228}}}, {"fair_coeff": 8.0, "zdim": 15, "test_results": {"test": {"acc": 0.8661971830985915, "DP": 0.10300250208507092, "EO": 0.08307461873638339, "CF": 0.05059720022261228}}}, {"fair_coeff": 8.0, "zdim": 16, "test_results": {"test": {"acc": 0.8661971830985915, "DP": 0.10300250208507092, "EO": 0.08307461873638339, "CF": 0.05059720022261228}}}, {"fair_coeff": 8.0, "zdim": 17, "test_results": {"test": {"acc": 0.8661971830985915, "DP": 0.10300250208507092, "EO": 0.08307461873638339, "CF": 0.05059720022261228}}}, {"fair_coeff": 8.0, "zdim": 18, "test_results": {"test": {"acc": 0.8661971830985915, "DP": 0.10300250208507092, "EO": 0.08307461873638339, "CF": 0.05059720022261228}}}, {"fair_coeff": 8.0, "zdim": 19, "test_results": {"test": {"acc": 0.8661971830985915, "DP": 0.10300250208507092, "EO": 0.08307461873638339, "CF": 0.05059720022261228}}}, {"fair_coeff": 8.0, "zdim": 20, "test_results": {"test": {"acc": 0.8661971830985915, "DP": 0.10300250208507092, "EO": 0.08307461873638339, "CF": 0.05059720022261228}}}, {"fair_coeff": 9.0, "zdim": 6, "test_results": {"test": {"acc": 0.852112676056338, "DP": 0.13052543786488743, "EO": 0.11068705259881728, "CF": 0.07183098591549296}}}, {"fair_coeff": 9.0, "zdim": 7, "test_results": {"test": {"acc": 0.852112676056338, "DP": 0.13052543786488743, "EO": 0.11068705259881728, "CF": 0.07183098591549296}}}, {"fair_coeff": 9.0, "zdim": 8, "test_results": {"test": {"acc": 0.852112676056338, "DP": 0.13052543786488743, "EO": 0.11068705259881728, "CF": 0.07183098591549296}}}, {"fair_coeff": 9.0, "zdim": 9, "test_results": {"test": {"acc": 0.852112676056338, "DP": 0.13052543786488743, "EO": 0.11068705259881728, "CF": 0.07183098591549296}}}, {"fair_coeff": 9.0, "zdim": 10, "test_results": {"test": {"acc": 0.852112676056338, "DP": 0.13052543786488743, "EO": 0.11068705259881728, "CF": 0.07183098591549296}}}, {"fair_coeff": 9.0, "zdim": 11, "test_results": {"test": {"acc": 0.852112676056338, "DP": 0.13052543786488743, "EO": 0.11068705259881728, "CF": 0.07183098591549296}}}, {"fair_coeff": 9.0, "zdim": 12, "test_results": {"test": {"acc": 0.852112676056338, "DP": 0.13052543786488743, "EO": 0.11068705259881728, "CF": 0.07183098591549296}}}, {"fair_coeff": 9.0, "zdim": 13, "test_results": {"test": {"acc": 0.852112676056338, "DP": 0.13052543786488743, "EO": 0.11068705259881728, "CF": 0.07183098591549296}}}, {"fair_coeff": 9.0, "zdim": 14, "test_results": {"test": {"acc": 0.852112676056338, "DP": 0.13052543786488743, "EO": 0.11068705259881728, "CF": 0.07183098591549296}}}, {"fair_coeff": 9.0, "zdim": 15, "test_results": {"test": {"acc": 0.852112676056338, "DP": 0.13052543786488743, "EO": 0.11068705259881728, "CF": 0.07183098591549296}}}, {"fair_coeff": 9.0, "zdim": 16, "test_results": {"test": {"acc": 0.852112676056338, "DP": 0.13052543786488743, "EO": 0.11068705259881728, "CF": 0.07183098591549296}}}, {"fair_coeff": 9.0, "zdim": 17, "test_results": {"test": {"acc": 0.852112676056338, "DP": 0.13052543786488743, "EO": 0.11068705259881728, "CF": 0.07183098591549296}}}, {"fair_coeff": 9.0, "zdim": 18, "test_results": {"test": {"acc": 0.852112676056338, "DP": 0.13052543786488743, "EO": 0.11068705259881728, "CF": 0.07183098591549296}}}, {"fair_coeff": 9.0, "zdim": 19, "test_results": {"test": {"acc": 0.852112676056338, "DP": 0.13052543786488743, "EO": 0.11068705259881728, "CF": 0.07183098591549296}}}, {"fair_coeff": 9.0, "zdim": 20, "test_results": {"test": {"acc": 0.852112676056338, "DP": 0.13052543786488743, "EO": 0.11068705259881728, "CF": 0.07183098591549296}}}, {"fair_coeff": 10.0, "zdim": 6, "test_results": {"test": {"acc": 0.8485915492957746, "DP": 0.14289685849318878, "EO": 0.12146747587924053, "CF": 0.09139210261569417}}}, {"fair_coeff": 10.0, "zdim": 7, "test_results": {"test": {"acc": 0.8485915492957746, "DP": 0.14289685849318878, "EO": 0.12146747587924053, "CF": 0.09139210261569417}}}, {"fair_coeff": 10.0, "zdim": 8, "test_results": {"test": {"acc": 0.8485915492957746, "DP": 0.14289685849318878, "EO": 0.12146747587924053, "CF": 0.09139210261569417}}}, {"fair_coeff": 10.0, "zdim": 9, "test_results": {"test": {"acc": 0.8485915492957746, "DP": 0.14289685849318878, "EO": 0.12146747587924053, "CF": 0.09139210261569417}}}, {"fair_coeff": 10.0, "zdim": 10, "test_results": {"test": {"acc": 0.8485915492957746, "DP": 0.14289685849318878, "EO": 0.12146747587924053, "CF": 0.09139210261569417}}}, {"fair_coeff": 10.0, "zdim": 11, "test_results": {"test": {"acc": 0.8485915492957746, "DP": 0.14289685849318878, "EO": 0.12146747587924053, "CF": 0.09139210261569417}}}, {"fair_coeff": 10.0, "zdim": 12, "test_results": {"test": {"acc": 0.8485915492957746, "DP": 0.14289685849318878, "EO": 0.12146747587924053, "CF": 0.09139210261569417}}}, {"fair_coeff": 10.0, "zdim": 13, "test_results": {"test": {"acc": 0.8485915492957746, "DP": 0.14289685849318878, "EO": 0.12146747587924053, "CF": 0.09139210261569417}}}, {"fair_coeff": 10.0, "zdim": 14, "test_results": {"test": {"acc": 0.8485915492957746, "DP": 0.14289685849318878, "EO": 0.12146747587924053, "CF": 0.09139210261569417}}}, {"fair_coeff": 10.0, "zdim": 15, "test_results": {"test": {"acc": 0.8485915492957746, "DP": 0.14289685849318878, "EO": 0.12146747587924053, "CF": 0.09139210261569417}}}, {"fair_coeff": 10.0, "zdim": 16, "test_results": {"test": {"acc": 0.8485915492957746, "DP": 0.14289685849318878, "EO": 0.12146747587924053, "CF": 0.09139210261569417}}}, {"fair_coeff": 10.0, "zdim": 17, "test_results": {"test": {"acc": 0.8485915492957746, "DP": 0.14289685849318878, "EO": 0.12146747587924053, "CF": 0.09139210261569417}}}, {"fair_coeff": 10.0, "zdim": 18, "test_results": {"test": {"acc": 0.8485915492957746, "DP": 0.14289685849318878, "EO": 0.12146747587924053, "CF": 0.09139210261569417}}}, {"fair_coeff": 10.0, "zdim": 19, "test_results": {"test": {"acc": 0.8485915492957746, "DP": 0.14289685849318878, "EO": 0.12146747587924053, "CF": 0.09139210261569417}}}, {"fair_coeff": 10.0, "zdim": 20, "test_results": {"test": {"acc": 0.8485915492957746, "DP": 0.14289685849318878, "EO": 0.12146747587924053, "CF": 0.09139210261569417}}}, {"fair_coeff": 15.0, "zdim": 6, "test_results": {"test": {"acc": 0.8661971830985915, "DP": 0.11217681401167642, "EO": 0.09216853408029876, "CF": 0.05130784708249497}}}, {"fair_coeff": 15.0, "zdim": 7, "test_results": {"test": {"acc": 0.8661971830985915, "DP": 0.11217681401167642, "EO": 0.09216853408029876, "CF": 0.05130784708249497}}}, {"fair_coeff": 15.0, "zdim": 8, "test_results": {"test": {"acc": 0.8661971830985915, "DP": 0.11217681401167642, "EO": 0.09216853408029876, "CF": 0.05130784708249497}}}, {"fair_coeff": 15.0, "zdim": 9, "test_results": {"test": {"acc": 0.8661971830985915, "DP": 0.11217681401167642, "EO": 0.09216853408029876, "CF": 0.05130784708249497}}}, {"fair_coeff": 15.0, "zdim": 10, "test_results": {"test": {"acc": 0.8661971830985915, "DP": 0.11217681401167642, "EO": 0.09216853408029876, "CF": 0.05130784708249497}}}, {"fair_coeff": 15.0, "zdim": 11, "test_results": {"test": {"acc": 0.8661971830985915, "DP": 0.11217681401167642, "EO": 0.09216853408029876, "CF": 0.05130784708249497}}}, {"fair_coeff": 15.0, "zdim": 12, "test_results": {"test": {"acc": 0.8661971830985915, "DP": 0.11217681401167642, "EO": 0.09216853408029876, "CF": 0.05130784708249497}}}, {"fair_coeff": 15.0, "zdim": 13, "test_results": {"test": {"acc": 0.8661971830985915, "DP": 0.11217681401167642, "EO": 0.09216853408029876, "CF": 0.05130784708249497}}}, {"fair_coeff": 15.0, "zdim": 14, "test_results": {"test": {"acc": 0.8661971830985915, "DP": 0.11217681401167642, "EO": 0.09216853408029876, "CF": 0.05130784708249497}}}, {"fair_coeff": 15.0, "zdim": 15, "test_results": {"test": {"acc": 0.8661971830985915, "DP": 0.11217681401167642, "EO": 0.09216853408029876, "CF": 0.05130784708249497}}}, {"fair_coeff": 15.0, "zdim": 16, "test_results": {"test": {"acc": 0.8661971830985915, "DP": 0.11217681401167642, "EO": 0.09216853408029876, "CF": 0.05130784708249497}}}, {"fair_coeff": 15.0, "zdim": 17, "test_results": {"test": {"acc": 0.8661971830985915, "DP": 0.11217681401167642, "EO": 0.09216853408029876, "CF": 0.05130784708249497}}}, {"fair_coeff": 15.0, "zdim": 18, "test_results": {"test": {"acc": 0.8661971830985915, "DP": 0.11217681401167642, "EO": 0.09216853408029876, "CF": 0.05130784708249497}}}, {"fair_coeff": 15.0, "zdim": 19, "test_results": {"test": {"acc": 0.8661971830985915, "DP": 0.11217681401167642, "EO": 0.09216853408029876, "CF": 0.05130784708249497}}}, {"fair_coeff": 15.0, "zdim": 20, "test_results": {"test": {"acc": 0.8661971830985915, "DP": 0.11217681401167642, "EO": 0.09216853408029876, "CF": 0.05130784708249497}}}, {"fair_coeff": 20.0, "zdim": 6, "test_results": {"test": {"acc": 0.8450704225352113, "DP": 0.138309702529886, "EO": 0.1170031901649548, "CF": 0.08626131790744467}}}, {"fair_coeff": 20.0, "zdim": 7, "test_results": {"test": {"acc": 0.8450704225352113, "DP": 0.138309702529886, "EO": 0.1170031901649548, "CF": 0.08626131790744467}}}, {"fair_coeff": 20.0, "zdim": 8, "test_results": {"test": {"acc": 0.8450704225352113, "DP": 0.138309702529886, "EO": 0.1170031901649548, "CF": 0.08626131790744467}}}, {"fair_coeff": 20.0, "zdim": 9, "test_results": {"test": {"acc": 0.8450704225352113, "DP": 0.138309702529886, "EO": 0.1170031901649548, "CF": 0.08626131790744467}}}, {"fair_coeff": 20.0, "zdim": 10, "test_results": {"test": {"acc": 0.8450704225352113, "DP": 0.138309702529886, "EO": 0.1170031901649548, "CF": 0.08626131790744467}}}, {"fair_coeff": 20.0, "zdim": 11, "test_results": {"test": {"acc": 0.8450704225352113, "DP": 0.138309702529886, "EO": 0.1170031901649548, "CF": 0.08626131790744467}}}, {"fair_coeff": 20.0, "zdim": 12, "test_results": {"test": {"acc": 0.8450704225352113, "DP": 0.138309702529886, "EO": 0.1170031901649548, "CF": 0.08626131790744467}}}, {"fair_coeff": 20.0, "zdim": 13, "test_results": {"test": {"acc": 0.8450704225352113, "DP": 0.138309702529886, "EO": 0.1170031901649548, "CF": 0.08626131790744467}}}, {"fair_coeff": 20.0, "zdim": 14, "test_results": {"test": {"acc": 0.8450704225352113, "DP": 0.138309702529886, "EO": 0.1170031901649548, "CF": 0.08626131790744467}}}, {"fair_coeff": 20.0, "zdim": 15, "test_results": {"test": {"acc": 0.8450704225352113, "DP": 0.138309702529886, "EO": 0.1170031901649548, "CF": 0.08626131790744467}}}, {"fair_coeff": 20.0, "zdim": 16, "test_results": {"test": {"acc": 0.8450704225352113, "DP": 0.138309702529886, "EO": 0.1170031901649548, "CF": 0.08626131790744467}}}, {"fair_coeff": 20.0, "zdim": 17, "test_results": {"test": {"acc": 0.8450704225352113, "DP": 0.138309702529886, "EO": 0.1170031901649548, "CF": 0.08626131790744467}}}, {"fair_coeff": 20.0, "zdim": 18, "test_results": {"test": {"acc": 0.8450704225352113, "DP": 0.138309702529886, "EO": 0.1170031901649548, "CF": 0.08626131790744467}}}, {"fair_coeff": 20.0, "zdim": 19, "test_results": {"test": {"acc": 0.8450704225352113, "DP": 0.138309702529886, "EO": 0.1170031901649548, "CF": 0.08626131790744467}}}, {"fair_coeff": 20.0, "zdim": 20, "test_results": {"test": {"acc": 0.8450704225352113, "DP": 0.138309702529886, "EO": 0.1170031901649548, "CF": 0.08626131790744467}}}]